envresolver/__init__.py
envresolver/envresolver.py
envresolver-1.0.0.dist-info/LICENSE.txt
envresolver-1.0.0.dist-info/METADATA
envresolver-1.0.0.dist-info/WHEEL
envresolver-1.0.0.dist-info/top_level.txt
envresolver-1.0.0.dist-info/RECORD
