Metadata-Version: 2.1
Name: envresolver
Version: 1.0.0
Summary: Pythonic parsing of environment variables
Home-page: https://github.com/jjstoo/envresolver
Author: Joni Lepistö
Author-email: joni.m.lepisto@gmail.com
License: apache-2.0
Download-URL: https://github.com/jjstoo/envresolver/releases
Keywords: environment,variable,variables,shell,parsing
Platform: UNKNOWN
Classifier: Development Status :: 5 - Production/Stable
Classifier: Intended Audience :: Developers
Classifier: Topic :: Software Development :: Libraries :: Python Modules
Classifier: License :: OSI Approved :: Apache Software License
Classifier: Programming Language :: Python :: 3
Classifier: Programming Language :: Python :: 3.8
Classifier: Programming Language :: Python :: 3.9
Classifier: Programming Language :: Python :: 3.10
License-File: LICENSE.txt
